polarion/__init__.py
polarion/document.py
polarion/factory.py
polarion/plan.py
polarion/polarion.py
polarion/project.py
polarion/record.py
polarion/testrun.py
polarion/user.py
polarion/utils.py
polarion/workitem.py
polarion/xml.py
polarion/base/__init__.py
polarion/base/comments.py
polarion/base/custom_fields.py
polarion/base/polarion_object.py
tests/__init__.py
tests/keys_template.py
tests/test_junit.py
tests/test_polarion_client.py
tests/test_polarion_document.py
tests/test_polarion_plan.py
tests/test_polarion_project.py
tests/test_polarion_test_record.py
tests/test_polarion_testrun.py
tests/test_polarion_user.py
tests/test_polarion_utils.py
tests/test_polarion_workitem.py
polarion-1.4.0.dist-info/LICENSE
polarion-1.4.0.dist-info/METADATA
polarion-1.4.0.dist-info/WHEEL
polarion-1.4.0.dist-info/top_level.txt
polarion-1.4.0.dist-info/RECORD
