Metadata-Version: 2.1
Name: polarion
Version: 1.4.0
Summary: Polarion client for Python
Home-page: https://github.com/jesper-raemaekers/python-polarion
Author: Jesper Raemaekers
Author-email: j.raemaekers@relek.nl
Project-URL: Bug Tracker, https://github.com/jesper-raemaekers/python-polarion/issues
Project-URL: Documentation, https://python-polarion.readthedocs.io/
Classifier: Programming Language :: Python :: 3
Classifier: License :: OSI Approved :: MIT License
Classifier: Operating System :: OS Independent
Classifier: Development Status :: 3 - Alpha
Requires-Python: >=3.7
License-File: LICENSE
Requires-Dist: zeep
Requires-Dist: lxml
Requires-Dist: texttable
